bulkfilechanger/__init__.py
bulkfilechanger/__main__.py
bulkfilechanger/bulkfilechanger.py
bulkfilechanger/main.py
bulkfilechanger/utils/__init__.py
bulkfilechanger/utils/commoncmd.py
bulkfilechanger/utils/crawler.py
BulkFileChanger-0.0.2.dist-info/LICENSE
BulkFileChanger-0.0.2.dist-info/METADATA
BulkFileChanger-0.0.2.dist-info/WHEEL
BulkFileChanger-0.0.2.dist-info/entry_points.txt
BulkFileChanger-0.0.2.dist-info/top_level.txt
BulkFileChanger-0.0.2.dist-info/RECORD
